{
  "slug": "blackboxstocks-options-flow-guide",
  "title": "How to Use BlackBoxStocks for Options Flow Analysis (2026)",
  "meta_title": "How to Use BlackBoxStocks for Options Flow Analysis (2026) | TradingToolsHub",
  "meta_description": "How to Use BlackBoxStocks for Options Flow Analysis (2026). BlackBoxStocks (4.1\u2605, $79.97/mo). Step-by-step setup, features walkthrough, and pro tips. Updated 20",
  "excerpt": "Complete options-flow guide for BlackBoxStocks.",
  "content": "<h2>What Is Options Flow and Why Does It Matter?</h2>\n<p>Options flow represents the real-time transactions and activity in the options market\u2014specifically the buying and selling of call and put contracts at various strike prices and expirations. When institutional traders, market makers, or large investors execute options trades, they leave a \"footprint\" in the form of volume spikes, unusual contract volume, and price movements at specific levels. Dark pool data reveals large block trades that occur off public exchanges, often signaling institutional conviction before moves become obvious to retail traders. Understanding options flow matters because it provides transparency into what <strong>smart money</strong> is positioning for. A sudden surge in call buying at a specific strike price, or large puts accumulating ahead of earnings, can signal institutional anticipation of price moves hours or days before retail traders notice. BlackBoxStocks surfaces this activity in real-time, turning raw options market data into actionable intelligence for traders who know how to read it.</p>\n<h2>How BlackBoxStocks Tracks Options Flow</h2>\n<p>BlackBoxStocks aggregates multiple data streams to create a comprehensive options flow scanner. Here's what the platform monitors:</p>\n<ul>\n<li><strong>Real-Time Flow Alerts:</strong> BlackBoxStocks displays live options transactions across major US exchanges, including sweeps (aggressive trades that hit multiple price levels), blocks (large single transactions), and splits (orders broken into smaller pieces to minimize market impact). These alerts stream in real-time, with color-coding and size metrics so you instantly recognize institutional-sized activity.</li>\n<li><strong>Dark Pool Prints:</strong> The platform captures dark pool options data, revealing large trades executed away from public exchanges. This is critical because dark pools often precede public market moves\u2014institutions frequently execute blocks in dark pools before the retail market sees the activity.</li>\n<li><strong>Unusual Activity Detection:</strong> BlackBoxStocks' AI engine flags unusual spikes in options volume, open interest accumulation, and implied volatility changes. Instead of manually scanning hundreds of data points, the AI highlights anomalies that statistically warrant attention.</li>\n<li><strong>Open Interest Trends:</strong> The platform tracks how open interest is shifting across strikes and expirations, revealing where institutional capital is building positions. Growing open interest at a specific strike is often a precursor to a test of that level.</li>\n<li><strong>Mobile and Desktop Monitoring:</strong> BlackBoxStocks' mobile app ensures you don't miss alerts on the go. Push notifications trigger when your custom thresholds are hit, so you can catch moves whether you're at your desk or away from screens.</li>\n</ul>\n<p>What sets BlackBoxStocks apart is the integration of these signals into a cohesive workflow. Rather than monitoring separate feeds, you get a unified dashboard where flow, alerts, and community sentiment converge.</p>\n<h2>Setting Up BlackBoxStocks for Options Flow Analysis</h2>\n<p>Getting the most from BlackBoxStocks requires intentional configuration. Here's how to build a setup that catches high-quality flow signals:</p>\n<ul>\n<li><strong>Step 1: Define Your Stock Universe.</strong> Use BlackBoxStocks' stock screener to narrow down to the liquid equities you trade. Filter by average daily volume, price range, and sector focus. This prevents alert fatigue by limiting signals to tradeable, liquid names.</li>\n<li><strong>Step 2: Set Flow Alert Thresholds.</strong> Configure minimum transaction sizes for sweeps, blocks, and splits. The Options Plus and higher tiers allow granular thresholds. For example, you might alert on puts over 500 contracts or calls hitting support levels with 10k+ premium. Lower thresholds increase signal frequency; higher thresholds catch only truly institutional activity.</li>\n<li><strong>Step 3: Configure Strike Price Filters.</strong> BlackBoxStocks allows you to focus on specific strike zones\u2014only alert on options near current price, or monitor accumulation at future support/resistance levels. This reduces noise from far out-of-the-money speculation.</li>\n<li><strong>Step 4: Activate Dark Pool Monitoring.</strong> Enable dark pool alerts for your watchlist. Institutional dark pool prints often precede public market moves and are one of the most predictive flow signals on the platform.</li>\n<li><strong>Step 5: Use the Alert Delivery System.</strong> Set alerts to push to your phone, email, or desktop. Many pro traders use Telegram integration (available via BlackBoxStocks Community features) to get intraday updates without cluttering email.</li>\n<li><strong>Step 6: Customize Your Flow Feed.</strong> Arrange the main flow feed to show the metrics that matter most to you\u2014contract volume, premium size, bid-ask spread, and implied volatility change. Some traders prioritize sweep activity; others focus on block accumulation in specific expiration months.</li>\n</ul>\n<p>The key to effective setup is <strong>eliminating false signals</strong>. Most beginners turn on all alerts and get overwhelmed. Pro users set thresholds high enough to catch only institutional-sized activity worth your trading capital.</p>\n<h2>Reading Options Flow Signals in BlackBoxStocks</h2>\n<p>Once set up, BlackBoxStocks displays options flow in real-time. Understanding what you're seeing is critical:</p>\n<ul>\n<li><strong>Sweeps vs. Blocks:</strong> A <strong>sweep</strong> is an aggressive order that hits multiple ask or bid prices simultaneously\u2014the trader wants immediate execution and is willing to pay the spread. Sweeps are highly directional and signal urgency. A <strong>block</strong> is a single large transaction, often at a single price level. Blocks can indicate either directional conviction or hedging (institutional funds buying puts to protect portfolios). BlackBoxStocks shows you both in real-time with volume and premium metrics so you can distinguish them.</li>\n<li><strong>Size and Premium Matter:</strong> A 1,000-contract sweep at a $2 call is different from a 5,000-contract sweep. BlackBoxStocks displays both contract count and total premium (contracts \u00d7 option price), allowing you to weigh institutional conviction. Higher premium indicates larger capital deployment.</li>\n<li><strong>Timing Relative to Price Action:</strong> Options flow is most predictive when it precedes price movement. If BlackBoxStocks alerts you to a large call sweep 30 minutes before a stock rallies, that's a valid signal. If the sweep comes after a 5% move, it's likely traders hedging or taking profits\u2014different implications entirely.</li>\n<li><strong>Distinguishing Hedging from Directional Bets:</strong> This is subtle. Puts bought on strength (when the stock is up) often signal hedging by long shareholders. Puts bought on weakness or at support signal directional bearish conviction. Calls bought near resistance suggest traders expect a breakout; calls at support suggest dip-buying by smart money. BlackBoxStocks' community chat and trade flow data help you calibrate these distinctions.</li>\n<li><strong>Open Interest Shifts:</strong> When BlackBoxStocks shows a particular strike accumulating open interest across multiple days, institutional traders are building positions. This often precedes a test of that strike level. Conversely, declining open interest suggests position unwinding.</li>\n</ul>\n<h2>Practical Options Flow Trading Strategies</h2>\n<p>Here are four proven strategies BlackBoxStocks users employ to capitalize on flow data:</p>\n<ul>\n<li><strong>1. Follow the Sweep:</strong> When BlackBoxStocks alerts you to a large call sweep at a key resistance level, treat it as institutional buying intent. Set a buy order near current support and target the resistance level where the sweep occurred. Example: If a stock is testing $150 support and BlackBoxStocks shows a 2,000-contract call sweep at the $155 strike, consider a directional trade targeting $155. Use BlackBoxStocks' live flow feed to confirm buying pressure as you hold the position. Exit if dark pool data shows large puts accumulating (profit-taking by institutions).</li>\n<li><strong>2. Contrarian Dark Pool Play:</strong> When BlackBoxStocks shows heavy dark pool put buying during an intraday rally, it often signals institutions hedging long positions into resistance\u2014a sign the move might be nearing exhaustion. Sell into this put-buying with a tight stop above recent highs. This is contrarian because retail traders see green and buy; the dark pool data shows sophisticated traders defending.</li>\n<li><strong>3. Unusual Open Interest Buildup:</strong> Use BlackBoxStocks' AI alerts to catch unusual growth in open interest at a specific strike and expiration. If a stock is at $100 and BlackBoxStocks shows $110 calls suddenly accumulating 50k contracts, traders are expecting an $10 move. Trade into the implied direction with a profit target near the accumulated strike. Manage risk tightly\u2014not all unusual OI builds pan out, but statistically they offer edge.</li>\n<li><strong>4. Community-Informed Flow Trading:</strong> BlackBoxStocks includes a live trading community where active users share observations. Cross-reference BlackBoxStocks flow data with community sentiment. If flow data shows call buying and community members independently identify the same setup, conviction increases. Use the mobile app to monitor both simultaneously during market hours.</li>\n</ul>\n<h2>BlackBoxStocks vs. Other Options Flow Tools</h2>\n<p>Several platforms compete in the options flow space. Here's how BlackBoxStocks stacks up:</p>\n<ul>\n<li><strong>vs. ThinkorSwim (TD Ameritrade):</strong> ThinkorSwim offers excellent charting and broker integration, but its options flow data is delayed and alerts are less sophisticated. BlackBoxStocks provides real-time flow with AI-powered unusual activity flags, making it superior for pure flow traders. However, ThinkorSwim integrates order execution, eliminating the need for a separate broker. Read our <a href=\"/compare/blackboxstocks-vs-thinkorswim/\">BlackBoxStocks vs. ThinkorSwim comparison</a> for details.</li>\n<li><strong>vs. Benzinga Pro:</strong> Benzinga offers excellent news and analyst alerts but limited options-specific flow data. BlackBoxStocks focuses specifically on options flow, dark pools, and unusual activity\u2014far more granular for options traders. Benzinga is better for swing traders; BlackBoxStocks suits day traders and flow specialists.</li>\n<li><strong>vs. OptionStrat:</strong> OptionStrat excels at options scanning and strategy identification but provides limited real-time flow. BlackBoxStocks' advantage is real-time dark pool data and community features, creating an environment where traders share and validate flow signals collaboratively.</li>\n</ul>\n<p>Overall, BlackBoxStocks is the strongest choice if <strong>real-time options flow and dark pool visibility</strong> are your primary needs. Its pricing starts at $59/month (Options Basic), scaling to $149/month for the full suite.</p>\n<h2>Is BlackBoxStocks Worth It for Options Flow?</h2>\n<p>BlackBoxStocks is not for everyone\u2014nor is it a magic money machine. Here's an honest assessment:</p>\n<p><strong>Best For:</strong> Active options traders who execute 5+ trades per week, traders who trade the same liquid stocks repeatedly, and community-oriented traders who benefit from peer discussion. If you're spending $1,000+ per month on trading, the $79-$149 platform cost is negligible. If you execute 1-2 trades per month, it's overkill.</p>\n<p><strong>Key Limitations:</strong> BlackBoxStocks provides data and alerts, not trading signals. You must interpret flow yourself. Beginners often misread signals (treating every block as institutional conviction, for example) and lose money. Additionally, BlackBoxStocks has no broker integration\u2014you must execute trades separately, adding friction. And there's no free trial, so you commit financially without testing the platform first.</p>\n<p><strong>The Real Edge:</strong> BlackBoxStocks' value lies in reducing information asymmetry. Retail traders normally see price and volume; institutional traders see dark pools and unusual options activity. BlackBoxStocks puts retail traders closer to the information institutions see. That edge, combined with discipline and proper trade management, is worth the subscription for active traders.</p>\n<p>For a detailed evaluation, see our full <a href=\"/review/blackboxstocks/\">BlackBoxStocks review</a>.</p>",
  "category": "options-flow",
  "tags": [
    "BlackBoxStocks",
    "options platforms"
  ],
  "author": "TradingToolsHub Editorial",
  "published_date": "2026-04-20",
  "last_updated": "2026-04-20",
  "read_time_minutes": 6,
  "image": "/blog/blackboxstocks-options-flow-guide.png",
  "image_alt": "BlackBoxStocks options-flow guide \u2014 TradingToolsHub",
  "related_tools": [
    "blackboxstocks",
    "optionsstrat",
    "flowalgo",
    "option-alpha"
  ],
  "related_comparisons": [],
  "target_keyword": "blackboxstocks options flow"
}