{
  "slug": "lucid-trading-tips-and-tricks",
  "title": "Lucid Trading Tips and Tricks Every Trader Should Know (2026)",
  "meta_title": "Lucid Trading Tips and Tricks Every Trader Should Know (2026) | TradingToolsHub",
  "meta_description": "Lucid Trading Tips and Tricks Every Trader Should Know (2026). Lucid Trading (4.5\u2605, Free). Pro tips, hidden features, and common mistakes to avoid. Updated 2026",
  "excerpt": "Insider tips and tricks for Lucid Trading that most traders never discover. Level up your workflow.",
  "content": "<p>I'll write a comprehensive tips and tricks guide for Lucid Trading based on the tool data you've provided. Let me create engaging, specific content that addresses power-user scenarios.</p>\n<p><h2>Why Lucid Trading Tips Matter</h2>\n<p>Most Lucid Trading traders activate an account and start trading without unlocking the platform's competitive advantages\u2014the 15-minute payouts, dual data feeds, and rule-flexible accounts that set it apart from older prop firms. This guide covers the strategic setup and operational workflows that separate profitable traders from those grinding against unnecessary friction. Understanding how to structure your account choice, optimize your data feed, and leverage Lucid Trading's fastest-in-class payout speed can compound into significant edge over a trading year.</p></p>\n<p><h2>Setup Tips</h2>\n<p><strong>Tip 1: Choose Your Account Tier Based on Actual Capital Requirements, Not Trading Psychology</strong></p>\n<p>Lucid Trading's tier system\u2014LucidFlex and LucidPro at $25K/$50K/$100K lines\u2014tempts traders to grab the smallest tier to \"prove themselves.\" Resist this. Your account choice determines whether you hit max daily loss limits during volatile NFP days. LucidFlex ($25K/$50K) has <em>no daily loss limit and no consistency rule</em> in the funded stage, making it the rare choice for high-volatility news traders and order-flow specialists who accept occasional 5-10% drawdowns. LucidPro adds consistency requirements but unlocks 100% of your first $10K in withdrawals <em>before</em> the 90% split applies\u2014a massive cash-flow advantage if you're profitable. Run paper trading on your target tier for 2 weeks before funding to validate whether the rules feel constraining.</p>\n<p><strong>Tip 2: Pre-Configure Your Data Feed Before Activation (CQG vs. Rithmic)</strong></p>\n<p>Lucid Trading offers both CQG and Rithmic feeds\u2014each with different latency profiles and order-flow visualizations. If you trade order-flow strategies on Sierra Chart or Quantower, Rithmic's footprint charts and volume profile tools are non-negotiable; CQG dominates if you're using MotiveWave or running algo strategies that prioritize tick data reliability. <strong>Select your feed during account setup, not after.</strong> Switching later requires re-authentication and risks missing market hours during the transition. Test both in the paper-trading environment for a full session (including your highest-volume market window) to feel latency and execution order quality.</p>\n<p><strong>Tip 3: Link Your Withdrawal Wallet During Onboarding</strong></p>\n<p>Lucid Trading's 15-minute average payout processing is meaningless if you spend 2 hours connecting your withdrawal destination. Set up your crypto wallet or bank account in your profile settings the moment your account activates. If using stable coins or crypto withdrawals, ensure your exchange deposit addresses are whitelisted in your security settings\u2014failed deposits cost you time. For bank transfers, confirm your account details match your legal name exactly to avoid processing delays that negate the speed advantage.</p>\n<p><strong>Tip 4: Enable API Access and Sandbox Mode Immediately for Algo Traders</strong></p>\n<p>If you're running automated strategies, activate Lucid Trading's API sandbox environment from day one. This lets you deploy your bots in a live-data environment without risking capital while you validate order routing, risk limits, and fill behavior. Most prop firms hide this in account settings; Lucid Trading's sandbox mirrors funded account rules, so bugs discovered here save real money later. Document your algorithm's max position size against Lucid Trading's leverage caps\u2014violations auto-liquidate without warning.</p>\n</p>\n<p><h2>Trading Tips</h2>\n<p><strong>Tip 1: Use the 15-Minute Payout Window as a Strategic Advantage, Not Just Speed</strong></p>\n<p>Lucid Trading's 15-minute average payout is industry-fastest, but most traders only use it to feel rich faster. Strategically, it means <em>you can compound intraday profits within the same session.</em> If you scalp ES for $500 profit by 10 AM, withdraw and reload by 10:15 AM to scale into a larger afternoon position on confirmed setup\u2014something impossible at firms with next-day payouts. Automate your withdrawal workflow: after consistent 3-trade wins, set a limit order to close, trigger your payout script, and stand ready to reload 15 minutes later.</p>\n<p><strong>Tip 2: Treat News Events (FOMC, NFP, CPI) as Your Dedicated Edge Window</strong></p>\n<p>Unlike many prop firms that restrict news trading, Lucid Trading explicitly permits FOMC, NFP, and CPI trades. If you have a documented news-trading strategy (mean reversion, breakout, volatility crush), <em>this is your differentiation.</em> Set up separate watchlists in your charting platform for 15-minute and 30-minute setups pre-event. Use the dual data feeds (CQG + Rithmic) to monitor order-flow divergence during the volatility spike\u2014if one feed shows scaled-in volume and the other shows reversal rejection, you've identified institutional flow position before retail traders. LucidFlex's unlimited daily drawdown is specifically built for traders who take 2-3 catastrophic news trades yearly but win big on setup execution.</p>\n<p><strong>Tip 3: Leverage Dual Data Feeds for Cross-Confirmation on Entry Signals</strong></p>\n<p>Having both CQG and Rithmic available simultaneously is rare. Open them side-by-side in your setup (CQG on one monitor, Rithmic on another if possible). When you spot a setup in one feed, confirm it in the other before entry. If CQG shows a volume spike with a narrow-range breakout but Rithmic shows bid/ask imbalance still favoring sellers, skip the trade\u2014the feeds are disagreeing on intent. Conversely, when both confirm (CQG volume + Rithmic volume profile showing absorption), your edge is higher. Document which feed has been more predictive for your specific markets and times of day.</p>\n<p><strong>Tip 4: Day-Trade Only\u2014Don't Test the Overnight Rules</strong></p>\n<p>Lucid Trading's day-trading requirement is strict: all positions must close intraday. Some traders try to exploit ambiguity by holding through the final minute hoping for a late-day reversal. <em>Don't.</em> The risk/reward is upside-down\u2014you might hold overnight for a $200 win but face account suspension if Lucid Trading's compliance interprets it as swing trading. Set hard cutoffs 15 minutes before market close and honor them religiously. Use a trailing stop during the last 10 minutes to lock in profits if you're still in a position.</p>\n<p><strong>Tip 5: Route Algorithms Through Quantower's \"Order-Flow Plus\" Module if Available on Your Plan</strong></p>\n<p>For algo traders, Quantower's integration with Lucid Trading feeds lets you visualize order-flow in real-time while your bot executes. Map the bot's entry conditions to a visual signal in Quantower (custom color on high-volume breakouts, for example) so you can audit live execution against your expected behavior. This catches silent failures where your algorithm issues no orders due to a condition-logic error.</p>\n<p><strong>Tip 6: Monitor Your Account's \"First $10K Withdrawal Priority\" on Pro/Direct Tiers</strong></p>\n<p>On LucidPro and LucidDirect, your first $10K earned monthly withdraws <em>before</em> the 90% split applies. This is huge: a $15K month yields $10K at 100% + $5K at 90% = $14,500 take-home. Many traders miss this and assume 90% splits apply to the entire profit. Track your monthly totals in a spreadsheet and time withdrawals strategically\u2014if you're $2K away from the $10K threshold with 2 days left in the month, an aggressive final push nets you an extra $200 in take-home.</p>\n</p>\n<p><h2>Risk Management Tips</h2>\n<p><strong>Tip 1: Exploit LucidFlex's Lack of Daily Loss Limit as a Controlled Variance Absorber</strong></p>\n<p>LucidFlex has no daily loss limit, which sounds reckless but is actually a feature for traders with high-conviction setups. If your strategy is +3R over 100 trades but has a risk of 4 consecutive -2R days, traditional prop-firm daily limits force you into emotional or mechanical changes. With LucidFlex, you can absorb that drawdown and recover. <strong>But use this responsibly:</strong> set a weekly loss limit in a spreadsheet (e.g., -$2K per week maximum). The no-daily-limit rule should not become an excuse to revenge-trade\u2014it's a variance management tool.</p>\n<p><strong>Tip 2: Calibrate Position Size Against Max Leverage, Not Just Account Balance</strong></p>\n<p>Lucid Trading's account tiers ($25K\u2013$150K) don't directly map to leverage limits. Confirm your exact leverage cap with support before deploying your full position-sizing algorithm. If you've coded your bot to use 10:1 leverage on a $50K LucidPro account and Lucid Trading's true limit is 8:1, your bot will risk hitting margin calls mid-session. Request your account's specific leverage table and embed it as a constant in your trading code to prevent oversizing.</p>\n<p><strong>Tip 3: Use Rithmic's Built-In Risk Dashboard to Monitor Real-Time Liquidation Distance</strong></p>\n<p>Rithmic displays your margin usage and distance to liquidation in real-time. Glance at it every 5 minutes during active trading. If you're more than 50% of the way to liquidation threshold, reduce your position size immediately\u2014don't wait for that third losing trade. Document your liquidation triggers in a note: \"At $X margin usage, flatten all positions and close the platform.\" This removes the emotion from risk decisions.</p>\n<p><strong>Tip 4: Log Every Rule Violation (Even Near-Misses) to Identify Compliance Blind Spots</strong></p>\n<p>Lucid Trading auto-enforces position-close and day-trading rules, but gray areas exist. If you've almost held a position overnight, you came close to a violation. Log it: date, time, reason you held, what stopped you. After 20 trades, review the log. If you see a pattern (\"I hold longer on volatile days\"), adjust your exit rules proactively before an actual breach triggers compliance review.</p>\n</p>\n<p><h2>Advanced Tips</h2>\n<p><strong>Tip 1: Automate Your Funding and Withdrawal Cycle with Webhook Monitoring</strong></p>\n<p>If Lucid Trading's API supports webhooks (confirm with their support), set up automated notifications when your profit hits $X threshold. You can then trigger a withdrawal request via API, wait the 15 minutes, and reinject capital into your account for the next session\u2014all without manual intervention. This is especially powerful for scalp traders hitting $500\u2013$1K profits per session: automate the cycle and you compound velocity without adding psychological friction.</p>\n<p><strong>Tip 2: Cross-Monitor Your Execution Quality Across Both Data Feeds</strong></p>\n<p>Set up a back-of-house monitoring spreadsheet that logs fill prices and latency on CQG vs. Rithmic for identical order types (e.g., your standard scalp entry). After 50 trades, calculate which feed gives you tighter fills on average. Some traders find CQG's execution superior for fast-moving breakouts; others find Rithmic's order-flow visibility more predictive. Quantify this and route your highest-conviction setups to the feed with empirical edge.</p>\n<p><strong>Tip 3: Synchronize Your Bot's Risk Model with Lucid Trading's Account Recovery Model</strong></p>\n<p>Lucid Trading's rules incentivize certain recovery arcs. On a $50K LucidPro account with a 4% daily max loss, a $2K loss day requires a $667+ win day to recover 50% of the drawdown. Some traders design their algorithms to be more aggressive on down days (wider stops, higher position counts) to hit this math. This is controversial but legal\u2014it's just position-sizing math aligned with the incentive structure. Decide your philosophy upfront: conservative recovery (same sizing every day) or proportional recovery (size up slightly after losses to hit breakeven faster).</p>\n<p><strong>Tip 4: Create a Custom \"Pre-Market Checklist\" Automation Script</strong></p>\n<p>Write a simple script (Python, Node.js, Bash) that runs 15 minutes before market open to validate: (1) both CQG and Rithmic are connected and showing current market data, (2) your withdrawal wallet shows a recent transaction in your records, (3) your account balance matches your position-sizing expectations, (4) no pending compliance warnings in your dashboard. Have the script send you a Slack/Telegram alert if any check fails. This catches setup problems before you're live and emotional.</p>\n<p><strong>Tip 5: Negotiate Your Payout Schedule for Consistency</strong></p>\n<p>If you're consistently profitable on a LucidPro account, reach out to Lucid Trading's support and ask if they offer recurring withdrawal schedules (automatic payouts every Friday, for example). Some firms build this for power users. Even if they don't officially advertise it, a consistent 5-figure monthly earner is valuable to them\u2014asking costs nothing and can save you 100+ manual withdrawal clicks per year.</p>\n</p>\n<p><h2>Common Mistakes to Avoid</h2>\n<p><strong>Mistake 1: Choosing LucidFlex for Psychological Comfort Instead of Strategic Fit</strong></p>\n<p><em>The problem:</em> New traders pick LucidFlex because \"no daily loss limit sounds less scary,\" then waste profitable edge by not properly capitalizing on it.</p>\n<p><em>The fix:</em> If you don't have a documented high-variance strategy (news trading, multi-trade setups, order-flow scalping), LucidPro's stricter rules and first-$10K withdrawal bonus are better. Use LucidFlex only if your backtests show you need variance absorption to be profitable long-term.</p>\n<p><strong>Mistake 2: Activating the Account Without Paper Trading on Your Chosen Tier First</strong></p>\n<p><em>The problem:</em> You fund a LucidPro account and immediately discover the consistency rules feel too tight for your trading style, but you've already committed capital.</p>\n<p><em>The fix:</em> Paper trade for 2 weeks on each tier before funding. Simulate your actual position size, market window, and setups. If the rules chafe, switch tiers. Paper trading costs nothing; guessing costs your P&amp;L.</p>\n<p><strong>Mistake 3: Ignoring the Data Feed as a Variable and Using Only One</strong></p>\n<p><em>The problem:</em> You activate an account, pick CQG because it's familiar, and never test Rithmic's order-flow data. You miss edge that would've been visible in footprints or volume profiles.</p>\n<p><em>The fix:</em> On your first trading day, open both feeds and glance between them for 30 minutes. If you spot signal divergence, investigate. Spend 1 hour per week in Rithmic's order-flow tools even if CQG is your primary\u2014you might discover a setup pattern that shows up clearest there.</p>\n<p><strong>Mistake 4: Treating the 15-Minute Payout as \"Free Money\" and Compounding Recklessly</strong></p>\n<p><em>The problem:</em> You profit $500, withdraw, reinject, and size up wildly because \"I can compound fast.\" Two losses wipe your gains and your reloaded capital simultaneously.</p>\n<p><em>The fix:</em> Automate your reinvestment only on profitable days. On losing days, withdraw your remaining balance and sit out the next session to preserve capital. Speed is an advantage; overleverage is a trap.</p>\n<p><strong>Mistake 5: Miscalculating the First-$10K Withdrawal Bonus Impact on Taxes</strong></p>\n<p><em>The problem:</em> On LucidPro, the first $10K pays at 100%, then 90% splits. Traders forget this affects their gross trading income for tax purposes\u2014you still owe taxes on the full 100%, not just your net take-home.</p>\n<p><em>The fix:</em> Consult a CPA familiar with prop-firm trading. Set aside 25% of your first $10K withdraw for tax liability. Lucid Trading should issue a 1099; verify it matches your records exactly to avoid audit risk.</p>\n</p>\n<p><h2>Lucid Trading vs Alternatives: When to Switch</h2>\n<p>Lucid Trading excels for futures day traders who need ultra-fast payouts, order-flow specialists, and algo developers on compatible platforms (Sierra Chart, Quantower, MotiveWave). However, if you're a swing trader, you'll hit the day-trading-only restriction hard\u2014look at <a href=\"/reviews/prop-firms\">full prop-firm comparisons</a> for firms allowing multi-day holds. If you need longer operating history and more generous daily loss limits, veteran firms like Prop Firm A or Prop Firm B have deeper compliance histories. For equities traders (not futures), Lucid Trading doesn't serve your market\u2014comparison pages are available in our <a href=\"/reviews/lucid-trading\">Lucid Trading full review</a> for equities-focused alternatives. Start with a $25K LucidFlex trial for 30 days; if the rules and payout speed fit your edge, scale to larger tiers.</p>\n</p>",
  "category": "tips",
  "tags": [
    "Lucid Trading",
    "prop firms",
    "tips",
    "tricks",
    "trading tips"
  ],
  "author": "TradingToolsHub Editorial",
  "published_date": "2026-04-26",
  "last_updated": "2026-04-26",
  "read_time_minutes": 9,
  "image": "/blog/lucid-trading-tips-and-tricks.png",
  "image_alt": "Lucid Trading tips guide \u2014 TradingToolsHub",
  "related_tools": [
    "lucid-trading",
    "alpha-futures",
    "ftmo",
    "funded-next-futures"
  ],
  "related_comparisons": [],
  "target_keyword": "lucid trading tips and tricks"
}